edu_irt/__init__.py
edu_irt/datas.py
edu_irt/graph.py
edu_irt/models.py
edu_irt/test.py
edu_irt-0.1.1.dist-info/LICENSE
edu_irt-0.1.1.dist-info/METADATA
edu_irt-0.1.1.dist-info/WHEEL
edu_irt-0.1.1.dist-info/top_level.txt
edu_irt-0.1.1.dist-info/RECORD
