Metadata-Version: 2.1
Name: edu-irt
Version: 0.1.1
Summary: created an IRT model for estimating item parameters
Home-page: https://github.com/glassesholder/edu_irt.git
Author: Hyojun LEE
Author-email: statisticlee@gmail.com
License: MIT
Platform: UNKNOWN
Classifier: Programming Language :: Python :: 3
Classifier: License :: OSI Approved :: MIT License
Classifier: Operating System :: OS Independent
Requires-Python: >=3.10
License-File: LICENSE
Requires-Dist: numpy>=2.1.2
Requires-Dist: pandas>=2.2.3
Requires-Dist: scipy>=1.14.1
Requires-Dist: matplotlib>=3.9.2
